gapred/__init__.py
gapred/core/__init__.py
gapred/core/layers.py
gapred/core/loss_functions.py
gapred/core/optimizers.py
gapred/core/simple_nn.py
gapred/core/tensor.py
gapred/reinforced/__init__.py
gapred/supervised/__init__.py
gapred/supervised/decision_tree.py
gapred/supervised/knn.py
gapred/supervised/linear_regression.py
gapred/supervised/naive_bayes.py
gapred/supervised/random_forest.py
gapred/unsupervised/__init__.py
gapred-0.9.2.dist-info/METADATA
gapred-0.9.2.dist-info/WHEEL
gapred-0.9.2.dist-info/top_level.txt
gapred-0.9.2.dist-info/RECORD
